tmoga/__init__.py
tmoga/main.py
tmoga/algorithm/Feature_Extraction.py
tmoga/algorithm/TMOGA.py
tmoga/algorithm/Transfer_Initialization.py
tmoga/algorithm/__init__.py
tmoga/utils/NSGA2.py
tmoga/utils/SDE.py
tmoga/utils/__init__.py
tmoga/utils/disjoint_set.py
tmoga/utils/evaluation.py
tmoga/utils/file_parser.py
tmoga/utils/visualization.py
tmoga-0.10.0.dist-info/METADATA
tmoga-0.10.0.dist-info/WHEEL
tmoga-0.10.0.dist-info/top_level.txt
tmoga-0.10.0.dist-info/RECORD
