Metadata-Version: 2.1
Name: tmoga
Version: 0.10.0
Summary: TMOGA(feature Transfer based Multi-Objective Genetic algorithm) is a multi-objective genetic algorithm to solve community detection problem on dynamic networks.
Home-page: https://github.com/zjg540066169/TMOGA
Author: Jungang Zou
Author-email: jungang.zou@gmail.com
License: UNKNOWN
Project-URL: Code, https://github.com/zjg540066169/TMOGA
Platform: UNKNOWN
Classifier: Development Status :: 2 - Pre-Alpha
Classifier: Intended Audience :: Science/Research
Classifier: License :: OSI Approved :: Apache Software License
Classifier: Natural Language :: English
Classifier: Operating System :: OS Independent
Classifier: Programming Language :: Python
Classifier: Programming Language :: Python :: 3 :: Only
Classifier: Programming Language :: Python :: 3.7
Classifier: Programming Language :: Python :: 3.8
Classifier: Programming Language :: Python :: 3.9
Classifier: Topic :: Scientific/Engineering :: Artificial Intelligence
Requires-Python: >=3.7.*
Requires-Dist: networkx (>=2.5)
Requires-Dist: argparse (>=1.1)
Requires-Dist: python-louvain (>=0.15)
Requires-Dist: joblib (>=0.17.0)
Requires-Dist: tqdm (>=4.50.2)
Requires-Dist: numpy (>=1.19.2)
Requires-Dist: matplotlib (>=3.3.2)
Requires-Dist: scikit-learn (>=0.23)
Requires-Dist: pandas (>=1.1.3)
